detoxify/__init__.py
detoxify/detoxify.py
detoxify-0.5.2.dist-info/LICENSE
detoxify-0.5.2.dist-info/METADATA
detoxify-0.5.2.dist-info/WHEEL
detoxify-0.5.2.dist-info/top_level.txt
detoxify-0.5.2.dist-info/RECORD
