Metadata-Version: 2.1
Name: detoxify
Version: 0.5.2
Summary: A python library for detecting toxic comments
Home-page: https://github.com/unitaryai/detoxify
Author: Unitary
Author-email: laura@unitary.ai
Classifier: Programming Language :: Python :: 3
Classifier: License :: OSI Approved :: Apache Software License
Classifier: Operating System :: OS Independent
Requires-Python: >=3.7
License-File: LICENSE
Requires-Dist: transformers
Requires-Dist: torch>=1.7.0
Requires-Dist: sentencepiece>=0.1.94
